fortigate_api/__init__.py
fortigate_api/cmdb/__init__.py
fortigate_api/cmdb/alertemail/__init__.py
fortigate_api/cmdb/alertemail/alertemail_c.py
fortigate_api/cmdb/alertemail/setting.py
fortigate_api/cmdb/antivirus/__init__.py
fortigate_api/cmdb/antivirus/antivirus_c.py
fortigate_api/cmdb/antivirus/heuristic.py
fortigate_api/cmdb/antivirus/profile.py
fortigate_api/cmdb/antivirus/quarantine.py
fortigate_api/cmdb/antivirus/settings.py
fortigate_api/cmdb/application/__init__.py
fortigate_api/cmdb/application/application_c.py
fortigate_api/cmdb/application/custom.py
fortigate_api/cmdb/application/group.py
fortigate_api/cmdb/application/list.py
fortigate_api/cmdb/application/name.py
fortigate_api/cmdb/application/rule_settings.py
fortigate_api/cmdb/authentication/__init__.py
fortigate_api/cmdb/authentication/authentication_c.py
fortigate_api/cmdb/authentication/rule.py
fortigate_api/cmdb/authentication/scheme.py
fortigate_api/cmdb/authentication/setting.py
fortigate_api/cmdb/certificate/__init__.py
fortigate_api/cmdb/certificate/ca.py
fortigate_api/cmdb/certificate/certificate_c.py
fortigate_api/cmdb/certificate/crl.py
fortigate_api/cmdb/certificate/local.py
fortigate_api/cmdb/certificate/remote.py
fortigate_api/cmdb/cmdb_s.py
fortigate_api/cmdb/credential_store/__init__.py
fortigate_api/cmdb/credential_store/credential_store_c.py
fortigate_api/cmdb/credential_store/domain_controller.py
fortigate_api/cmdb/dlp/__init__.py
fortigate_api/cmdb/dlp/dlp_c.py
fortigate_api/cmdb/dlp/filepattern.py
fortigate_api/cmdb/dlp/fp_doc_source.py
fortigate_api/cmdb/dlp/sensitivity.py
fortigate_api/cmdb/dlp/sensor.py
fortigate_api/cmdb/dlp/settings.py
fortigate_api/cmdb/dnsfilter/__init__.py
fortigate_api/cmdb/dnsfilter/dnsfilter_c.py
fortigate_api/cmdb/dnsfilter/domain_filter.py
fortigate_api/cmdb/dnsfilter/profile.py
fortigate_api/cmdb/emailfilter/__init__.py
fortigate_api/cmdb/emailfilter/bwl.py
fortigate_api/cmdb/emailfilter/bword.py
fortigate_api/cmdb/emailfilter/dnsbl.py
fortigate_api-2.0.2.dist-info/LICENCE.txt
fortigate_api-2.0.2.dist-info/METADATA
fortigate_api-2.0.2.dist-info/WHEEL
fortigate_api-2.0.2.dist-info/RECORD
