Metadata-Version: 2.1
Name: fortigate_api
Version: 2.0.2
Summary: Python package to configure Fortigate (Fortios) devices using REST API and SSH
Home-page: https://github.com/vladimirs-git/fortigate-api
License: Apache-2.0
Keywords: fortigate,fortios,rest,api
Author: Vladimirs Prusakovs
Author-email: vladimir.prusakovs@gmail.com
Requires-Python: >=3.8,<4.0
Classifier: Development Status :: 5 - Production/Stable
Classifier: Intended Audience :: Developers
Classifier: Intended Audience :: System Administrators
Classifier: Intended Audience :: Telecommunications Industry
Classifier: License :: OSI Approved :: Apache Software License
Classifier: Natural Language :: English
Classifier: Programming Language :: Python :: 3
Classifier: Programming Language :: Python :: 3.8
Classifier: Programming Language :: Python :: 3.9
Classifier: Programming Language :: Python :: 3.10
Classifier: Programming Language :: Python :: 3.11
Classifier: Programming Language :: Python :: 3.12
Classifier: Topic :: System :: Networking :: Firewalls
Provides-Extra: test
Requires-Dist: requests (>=2.28,<3.0)
Requires-Dist: vhelpers (>=0.1.17,<0.2.0)
Project-URL: Bug Tracker, https://github.com/vladimirs-git/fortigate-api/issues
Project-URL: Download URL, https://github.com/vladimirs-git/fortigate-api/archive/refs/tags/2.0.2.tar.gz
Project-URL: Repository, https://github.com/vladimirs-git/fortigate-api
